toggled_widgets/__init__.py
toggled_widgets/static/admin/css/ToggledWidget.css
toggled_widgets/static/admin/js/DjangoAdminFieldContext.js
toggled_widgets/static/admin/js/ToggledWidget.init.js
toggled_widgets/static/admin/js/ToggledWidget.js
django_toggled_widgets-0.8.dist-info/COPYING
django_toggled_widgets-0.8.dist-info/METADATA
django_toggled_widgets-0.8.dist-info/WHEEL
django_toggled_widgets-0.8.dist-info/top_level.txt
django_toggled_widgets-0.8.dist-info/RECORD
