Metadata-Version: 2.1
Name: django-toggled-widgets
Version: 0.8
Summary: Base classes and mixins to facilitate toggling visibility between multiple Django admin fields.
Home-page: https://github.com/mcrowepfx/REST-Client-Framework
Author: Max Crowe
Author-email: max.crowe@performics.com
Classifier: Programming Language :: Python :: 3
Classifier: License :: OSI Approved :: GNU General Public License v3 (GPLv3)
Classifier: Operating System :: OS Independent
Classifier: Framework :: Django
Requires-Python: >=3.6
License-File: COPYING
